carriercost/__init__.py
carriercost/calculator.py
carriercost/reader.py
carriercost-0.0.2.dist-info/DESCRIPTION.rst
carriercost-0.0.2.dist-info/METADATA
carriercost-0.0.2.dist-info/RECORD
carriercost-0.0.2.dist-info/WHEEL
carriercost-0.0.2.dist-info/metadata.json
carriercost-0.0.2.dist-info/top_level.txt
carriercost-0.0.2.dist-info/zip-safe
