Metadata-Version: 2.0
Name: carriercost
Version: 0.0.2
Summary: Calculate carrier cost.
Home-page: UNKNOWN
Author: qx3501332
Author-email: x.qiu@qq.com
License: MIT License
Platform: UNKNOWN
Classifier: Development Status :: 4 - Beta
Classifier: Intended Audience :: Developers
Classifier: Operating System :: OS Independent
Classifier: Programming Language :: Python :: 3.6
Classifier: Topic :: Software Development :: Libraries :: Python Modules
Requires-Dist: addlib
